{
  "data": {
    "clip": {
      "id": "1399001567",
      "slug": "UnusualEnchantingSproutGivePLZ-o5o0fw_2qOgZvAag",
      "url": "https://www.twitch.tv/xqc/clip/UnusualEnchantingSproutGivePLZ-o5o0fw_2qOgZvAag",
      "isAutoCurated": false,
      "embedURL": "https://clips.twitch.tv/embed?clip=UnusualEnchantingSproutGivePLZ-o5o0fw_2qOgZvAag",
      "title": "lol",
      "viewCount": 42402,
      "language": "EN",
      "isFeatured": false,
      "assets": [
        {
          "id": "785f4132-fc47-4fe1-a872-4b99af27f08f",
          "aspectRatio": 1.7777777777777777,
          "createdAt": "2026-02-04T04:07:37.331683814Z",
          "creationState": "CREATED",
          "curator": {
            "id": "768198835",
            "login": "puertoricanporo",
            "displayName": "puertoricanporo",
            "profileImageURL": "https://static-cdn.jtvnw.net/jtv_user_pictures/efc61fe3-285e-487e-a627-212860abe0cb-profile_image-50x50.png",
            "__typename": "User"
          },
          "thumbnailURL": "https://static-cdn.jtvnw.net/twitch-clips-thumbnails-prod/UnusualEnchantingSproutGivePLZ-o5o0fw_2qOgZvAag/785f4132-fc47-4fe1-a872-4b99af27f08f/preview.jpg",
          "videoQualities": [
            {
              "bitrate": 8004451,
              "codecs": "avc1.64002A,mp4a.40.2",
              "duration": null,
              "height": 1080,
              "width": 1920,
              "videoCodec": "AVC",
              "frameRate": 60,
              "quality": "1080",
              "sourceURL": "https://production.assets.clips.twitchcdn.net/v2/media/UnusualEnchantingSproutGivePLZ-o5o0fw_2qOgZvAag/785f4132-fc47-4fe1-a872-4b99af27f08f/video-1080.mp4",
              "__typename": "ClipVideoQuality"
            },
            {
              "bitrate": 0,
              "codecs": "",
              "duration": null,
              "height": 0,
              "width": 0,
              "videoCodec": "AVC",
              "frameRate": 60.011383056640625,
              "quality": "720",
              "sourceURL": "https://production.assets.clips.twitchcdn.net/v2/media/UnusualEnchantingSproutGivePLZ-o5o0fw_2qOgZvAag/785f4132-fc47-4fe1-a872-4b99af27f08f/video-720.mp4",
              "__typename": "ClipVideoQuality"
            },
            {
              "bitrate": 0,
              "codecs": "",
              "duration": null,
              "height": 0,
              "width": 0,
              "videoCodec": "AVC",
              "frameRate": 30.005691528320312,
              "quality": "480",
              "sourceURL": "https://production.assets.clips.twitchcdn.net/v2/media/UnusualEnchantingSproutGivePLZ-o5o0fw_2qOgZvAag/785f4132-fc47-4fe1-a872-4b99af27f08f/video-480.mp4",
              "__typename": "ClipVideoQuality"
            },
            {
              "bitrate": 0,
              "codecs": "",
              "duration": null,
              "height": 0,
              "width": 0,
              "videoCodec": "AVC",
              "frameRate": 30.005691528320312,
              "quality": "360",
              "sourceURL": "https://production.assets.clips.twitchcdn.net/v2/media/UnusualEnchantingSproutGivePLZ-o5o0fw_2qOgZvAag/785f4132-fc47-4fe1-a872-4b99af27f08f/video-360.mp4",
              "__typename": "ClipVideoQuality"
            }
          ],
          "portraitMetadata": null,
          "__typename": "ClipAsset"
        },
        {
          "id": "2fca5905-b991-446f-a1a9-4994cc5f0a13",
          "aspectRatio": 0.562,
          "createdAt": "2026-02-04T04:07:37.331683814Z",
          "creationState": "CREATED",
          "curator": {
            "id": "768198835",
            "login": "puertoricanporo",
            "displayName": "puertoricanporo",
            "profileImageURL": "https://static-cdn.jtvnw.net/jtv_user_pictures/efc61fe3-285e-487e-a627-212860abe0cb-profile_image-50x50.png",
            "__typename": "User"
          },
          "thumbnailURL": "https://static-cdn.jtvnw.net/twitch-clips-thumbnails-prod/UnusualEnchantingSproutGivePLZ-o5o0fw_2qOgZvAag/2fca5905-b991-446f-a1a9-4994cc5f0a13/preview-153x272.jpg",
          "videoQualities": [
            {
              "bitrate": 8004451,
              "codecs": "avc1.64002A,mp4a.40.2",
              "duration": null,
              "height": 1080,
              "width": 1920,
              "videoCodec": "AVC",
              "frameRate": 60,
              "quality": "607",
              "sourceURL": "https://production.assets.clips.twitchcdn.net/v2/media/UnusualEnchantingSproutGivePLZ-o5o0fw_2qOgZvAag/2fca5905-b991-446f-a1a9-4994cc5f0a13/video-607.mp4",
              "__typename": "ClipVideoQuality"
            },
            {
              "bitrate": 0,
              "codecs": "",
              "duration": null,
              "height": 0,
              "width": 0,
              "videoCodec": "AVC",
              "frameRate": 0,
              "quality": "480",
              "sourceURL": "",
              "__typename": "ClipVideoQuality"
            },
            {
              "bitrate": 0,
              "codecs": "",
              "duration": null,
              "height": 0,
              "width": 0,
              "videoCodec": "AVC",
              "frameRate": 0,
              "quality": "360",
              "sourceURL": "",
              "__typename": "ClipVideoQuality"
            }
          ],
          "portraitMetadata": {
            "portraitClipLayout": "FULL",
            "fullTemplateMetadata": {
              "mainFrame": {
                "topLeft": {
                  "xPercentage": 34.1796875,
                  "yPercentage": 0,
                  "__typename": "PortraitCropCoordinates"
                },
                "bottomRight": {
                  "xPercentage": 65.8203125,
                  "yPercentage": 100,
                  "__typename": "PortraitCropCoordinates"
                },
                "__typename": "PortraitCropMetadata"
              },
              "__typename": "FullTemplateMetadata"
            },
            "stackedTemplateMetadata": null,
            "__typename": "PortraitClipCropping"
          },
          "__typename": "ClipAsset"
        }
      ],
      "curator": {
        "id": "768198835",
        "login": "puertoricanporo",
        "displayName": "puertoricanporo",
        "profileImageURL": "https://static-cdn.jtvnw.net/jtv_user_pictures/efc61fe3-285e-487e-a627-212860abe0cb-profile_image-70x70.png",
        "__typename": "User"
      },
      "game": {
        "id": "23020",
        "name": "ROBLOX",
        "boxArtURL": "https://static-cdn.jtvnw.net/ttv-boxart/23020_IGDB-52x72.jpg",
        "displayName": "ROBLOX",
        "slug": "roblox",
        "__typename": "Game"
      },
      "broadcast": {
        "id": "317190764640",
        "title": null,
        "__typename": "Broadcast"
      },
      "broadcaster": {
        "id": "71092938",
        "login": "xqc",
        "displayName": "xQc",
        "primaryColorHex": "FFBF00",
        "isPartner": true,
        "profileImageURL": "https://static-cdn.jtvnw.net/jtv_user_pictures/xqc-profile_image-9298dca608632101-70x70.jpeg",
        "followers": {
          "totalCount": 12281541,
          "__typename": "FollowerConnection"
        },
        "stream": null,
        "lastBroadcast": {
          "id": "317179988830",
          "startedAt": "2026-02-07T08:20:33.772685Z",
          "__typename": "Broadcast"
        },
        "self": null,
        "__typename": "User"
      },
      "thumbnailURL": "https://static-cdn.jtvnw.net/twitch-clips-thumbnails-prod/UnusualEnchantingSproutGivePLZ-o5o0fw_2qOgZvAag/785f4132-fc47-4fe1-a872-4b99af27f08f/preview.jpg",
      "createdAt": "2026-02-04T04:07:37Z",
      "isPublished": true,
      "duration": 43.93,
      "durationSeconds": 43,
      "champBadge": null,
      "playbackAccessToken": {
        "signature": "da8884d7b1c8b1a493c291d2b55d28f1d3625932",
        "value": "{\"authorization\":{\"forbidden\":false,\"reason\":\"\"},\"clip_uri\":\"https://production.assets.clips.twitchcdn.net/v2/media/UnusualEnchantingSproutGivePLZ-o5o0fw_2qOgZvAag/2fca5905-b991-446f-a1a9-4994cc5f0a13/video-607.mp4\",\"clip_slug\":\"UnusualEnchantingSproutGivePLZ-o5o0fw_2qOgZvAag\",\"device_id\":null,\"expires\":1770625717,\"user_id\":\"\",\"version\":3}",
        "__typename": "PlaybackAccessToken"
      },
      "video": {
        "id": "2688404677",
        "broadcastType": "ARCHIVE",
        "title": "🙄LIVE🙄DRAMA🙄NEWS🙄CLICK🙄LOCK IN🙄WOW🙄COOL🙄LETS GO 🙄PULL UP🙄",
        "__typename": "Video"
      },
      "videoOffsetSeconds": 12062,
      "videoQualities": [
        {
          "sourceURL": "https://production.assets.clips.twitchcdn.net/v2/media/UnusualEnchantingSproutGivePLZ-o5o0fw_2qOgZvAag/785f4132-fc47-4fe1-a872-4b99af27f08f/video-1080.mp4",
          "__typename": "ClipVideoQuality"
        },
        {
          "sourceURL": "https://production.assets.clips.twitchcdn.net/v2/media/UnusualEnchantingSproutGivePLZ-o5o0fw_2qOgZvAag/785f4132-fc47-4fe1-a872-4b99af27f08f/video-720.mp4",
          "__typename": "ClipVideoQuality"
        },
        {
          "sourceURL": "https://production.assets.clips.twitchcdn.net/v2/media/UnusualEnchantingSproutGivePLZ-o5o0fw_2qOgZvAag/785f4132-fc47-4fe1-a872-4b99af27f08f/video-480.mp4",
          "__typename": "ClipVideoQuality"
        },
        {
          "sourceURL": "https://production.assets.clips.twitchcdn.net/v2/media/UnusualEnchantingSproutGivePLZ-o5o0fw_2qOgZvAag/785f4132-fc47-4fe1-a872-4b99af27f08f/video-360.mp4",
          "__typename": "ClipVideoQuality"
        }
      ],
      "isViewerEditRestricted": false,
      "suggestedCropping": null,
      "rawMediaRelativeOffset": 30.436817169189453,
      "rawMediaKey": "5V7n_TrusYjbKULZPgs8Og",
      "__typename": "Clip"
    }
  },
  "extensions": {
    "durationMilliseconds": 68,
    "operationName": "ShareClipRenderStatus",
    "requestID": "01KGYKKCY8Q8YDMZMMG1FQW7BX"
  }
}
